setup.cfg
setup.py
nexusadspy/__init__.py
nexusadspy/client.py
nexusadspy/exceptions.py
nexusadspy/report.py
nexusadspy/segment.py
nexusadspy.egg-info/PKG-INFO
nexusadspy.egg-info/SOURCES.txt
nexusadspy.egg-info/dependency_links.txt
nexusadspy.egg-info/not-zip-safe
nexusadspy.egg-info/top_level.txt