Metadata-Version: 1.1
Name: nexusadspy
Version: 0.3.4
Summary: Thin wrapper around AppNexus API
Home-page: https://github.com/markovianhq/nexusadspy
Author: Daniel Olel, Georg Walther
Author-email: daniel.olel@rocket-internet.com, georg.walther@markovian.com
License: UNKNOWN
Download-URL: https://github.com/markovianhq/nexusadspy/tarball/master
Keywords: nexuadspy appnexus api python
Platform: UNKNOWN
Classifier: Development Status :: 4 - Beta
Classifier: Intended Audience :: Developers
Classifier: Natural Language :: English
Classifier: Programming Language :: Python :: 2
Classifier: Programming Language :: Python :: 2.7
Classifier: Programming Language :: Python :: 3
Classifier: Programming Language :: Python :: 3.3
Classifier: Programming Language :: Python :: 3.4
Classifier: Programming Language :: Python :: 3.5
